{
 "authors": [
  {
   "last_commit": "4 months ago",
   "lines": 5,
   "percentage": 22.7,
   "author": "Todd Gamblin",
   "email": "<tgamblin@llnl.gov>"
  },
  {
   "last_commit": "10 months ago",
   "lines": 3,
   "percentage": 13.6,
   "author": "Tomoki, Karatsu",
   "email": "<49965247+t-karatsu@users.noreply.github.com>"
  },
  {
   "last_commit": "2 years ago",
   "lines": 7,
   "percentage": 31.8,
   "author": "Adam J. Stewart",
   "email": "<ajstewart426@gmail.com>"
  },
  {
   "last_commit": "2 years ago",
   "lines": 4,
   "percentage": 18.2,
   "author": "twang15",
   "email": "<twang15@ncsu.edu>"
  },
  {
   "last_commit": "5 years ago",
   "lines": 3,
   "percentage": 13.6,
   "author": "David Beckingsale",
   "email": "<davidbeckingsale@gmail.com>"
  }
 ],
 "totals": {
  "last_commit": "4 months ago",
  "lines": 22,
  "percentage": "100.0"
 }
}