{
 "authors": [
  {
   "last_commit": "yesterday",
   "lines": 7,
   "percentage": 20.0,
   "author": "shanedsnyder",
   "email": "<ssnyder@mcs.anl.gov>"
  },
  {
   "last_commit": "4 months ago",
   "lines": 4,
   "percentage": 11.4,
   "author": "Todd Gamblin",
   "email": "<tgamblin@llnl.gov>"
  },
  {
   "last_commit": "7 months ago",
   "lines": 1,
   "percentage": 2.9,
   "author": "ketsubouchi",
   "email": "<kenta.tsubouchi@hac-inc.co.jp>"
  },
  {
   "last_commit": "a year ago",
   "lines": 1,
   "percentage": 2.9,
   "author": "Carson Woods",
   "email": "<carsonwoods@users.noreply.github.com>"
  },
  {
   "last_commit": "a year ago",
   "lines": 1,
   "percentage": 2.9,
   "author": "Adam J. Stewart",
   "email": "<ajstewart426@gmail.com>"
  },
  {
   "last_commit": "2 years ago",
   "lines": 2,
   "percentage": 5.7,
   "author": "Francois Budin",
   "email": "<francois.budin@kitware.com>"
  },
  {
   "last_commit": "3 years ago",
   "lines": 2,
   "percentage": 5.7,
   "author": "carns",
   "email": "<carns@users.noreply.github.com>"
  },
  {
   "last_commit": "4 years ago",
   "lines": 1,
   "percentage": 2.9,
   "author": "\u5065\u7f8e\u732b",
   "email": "<weijianwen@gmail.com>"
  },
  {
   "last_commit": "4 years ago",
   "lines": 16,
   "percentage": 45.7,
   "author": "Pramod Kumbhar",
   "email": "<pramod.s.kumbhar@gmail.com>"
  }
 ],
 "totals": {
  "last_commit": "yesterday",
  "lines": 35,
  "percentage": "100.0"
 }
}