{
 "authors": [
  {
   "last_commit": "2 months ago",
   "lines": 6,
   "percentage": 13.0,
   "author": "Tomoki, Karatsu",
   "email": "<49965247+t-karatsu@users.noreply.github.com>"
  },
  {
   "last_commit": "4 months ago",
   "lines": 3,
   "percentage": 6.5,
   "author": "Todd Gamblin",
   "email": "<tgamblin@llnl.gov>"
  },
  {
   "last_commit": "4 months ago",
   "lines": 32,
   "percentage": 69.6,
   "author": "Adam J. Stewart",
   "email": "<ajstewart426@gmail.com>"
  },
  {
   "last_commit": "a year ago",
   "lines": 3,
   "percentage": 6.5,
   "author": "Andreas Baumbach",
   "email": "<healther@users.noreply.github.com>"
  },
  {
   "last_commit": "4 years ago",
   "lines": 2,
   "percentage": 4.3,
   "author": "Matthew Krafczyk",
   "email": "<krafczyk.matthew@gmail.com>"
  }
 ],
 "totals": {
  "last_commit": "2 months ago",
  "lines": 46,
  "percentage": "100.0"
 }
}