{
 "authors": [
  {
   "last_commit": "2 months ago",
   "lines": 3,
   "percentage": 10.0,
   "author": "Glenn Johnson",
   "email": "<glenn-johnson@uiowa.edu>"
  },
  {
   "last_commit": "a year ago",
   "lines": 13,
   "percentage": 43.3,
   "author": "Justin S",
   "email": "<3630356+codeandkey@users.noreply.github.com>"
  },
  {
   "last_commit": "2 years ago",
   "lines": 1,
   "percentage": 3.3,
   "author": "Levi Baber",
   "email": "<baberlevi@gmail.com>"
  },
  {
   "last_commit": "2 years ago",
   "lines": 2,
   "percentage": 6.7,
   "author": "Adam J. Stewart",
   "email": "<ajstewart426@gmail.com>"
  },
  {
   "last_commit": "3 years ago",
   "lines": 11,
   "percentage": 36.7,
   "author": "lingnanyuan",
   "email": "<1297162327@qq.com>"
  }
 ],
 "totals": {
  "last_commit": "2 months ago",
  "lines": 30,
  "percentage": "100.0"
 }
}