{
 "authors": [
  {
   "last_commit": "2 months ago",
   "lines": 36,
   "percentage": 13.6,
   "author": "Shintaro Iwasaki",
   "email": "<siwasaki@anl.gov>"
  },
  {
   "last_commit": "6 months ago",
   "lines": 5,
   "percentage": 1.9,
   "author": "Toyohisa Kameyama",
   "email": "<kameyama@riken.jp>"
  },
  {
   "last_commit": "a year ago",
   "lines": 224,
   "percentage": 84.5,
   "author": "Vivek Kale",
   "email": "<11766050+vlkale@users.noreply.github.com>"
  }
 ],
 "totals": {
  "last_commit": "2 months ago",
  "lines": 265,
  "percentage": "100.0"
 }
}