{
 "authors": [
  {
   "last_commit": "a month ago",
   "lines": 2,
   "percentage": 2.5,
   "author": "darmac",
   "email": "<xiaojun2@hisilicon.com>"
  },
  {
   "last_commit": "a year ago",
   "lines": 1,
   "percentage": 1.3,
   "author": "Seth R. Johnson",
   "email": "<johnsonsr@ornl.gov>"
  },
  {
   "last_commit": "2 years ago",
   "lines": 76,
   "percentage": 96.2,
   "author": "Neil Flood",
   "email": "<neilflood@fastmail.fm>"
  }
 ],
 "totals": {
  "last_commit": "a month ago",
  "lines": 79,
  "percentage": "100.0"
 }
}